mdgpt/__init__.py
mdgpt/build.py
mdgpt/engines.yaml
mdgpt/image.py
mdgpt/models.py
mdgpt/translate.py
mdgpt/utils.py
mdgpt-0.3.5.dist-info/entry_points.txt
mdgpt-0.3.5.dist-info/LICENSE
mdgpt-0.3.5.dist-info/WHEEL
mdgpt-0.3.5.dist-info/METADATA
mdgpt-0.3.5.dist-info/RECORD
