Metadata-Version: 2.1
Name: mdgpt
Version: 0.3.5
Summary: Translate markdown files using OpenAI ChatGPT, and generate localized copies of each file.
Home-page: https://github.com/Djarnis/mdGPT
License: MIT
Keywords: markdown,translation,openai,chatgpt,gpt
Author: Jeppe Bårris
Author-email: jeppe@barris.dk
Requires-Python: >=3.10,<4.0
Classifier: License :: OSI Approved :: MIT License
Classifier: Programming Language :: Python :: 3
Classifier: Programming Language :: Python :: 3.10
Requires-Dist: Pillow (>=10.0.0,<11.0.0)
Requires-Dist: openai (>=0.27.8,<0.28.0)
Requires-Dist: pycountry (>=22.3.5,<23.0.0)
Requires-Dist: pydantic (>=2.0.3,<3.0.0)
Requires-Dist: python-dotenv (>=1.0.0,<2.0.0)
Requires-Dist: python-frontmatter (>=1.0.0,<2.0.0)
Requires-Dist: python-slugify (>=8.0.1,<9.0.0)
Requires-Dist: requests (>=2.31.0,<3.0.0)
Requires-Dist: rich (>=13.4.2,<14.0.0)
Project-URL: Repository, https://github.com/Djarnis/mdGPT
